publishable_model/__init__.py
publishable_model/apps.py
publishable_model/managers.py
publishable_model/models.py
publishable_model/querysets.py
publishable_model/settings.py
publishable_model/admin/__init__.py
publishable_model/admin/admin.py
publishable_model/admin/admin_filters.py
django_publishable_model-0.1.5.dist-info/LICENSE.md
django_publishable_model-0.1.5.dist-info/METADATA
django_publishable_model-0.1.5.dist-info/WHEEL
django_publishable_model-0.1.5.dist-info/top_level.txt
django_publishable_model-0.1.5.dist-info/RECORD
