Metadata-Version: 2.1
Name: django-publishable-model
Version: 0.1.5
Summary: Make your models publishable in an easy way, the admin will be smart and easily configurable
Home-page: https://github.com/frankhood/django-publishable-model
Author: FrankHood Business Solutions srl
Author-email: info@frankhood.it
License: MIT
Keywords: django-publishable-model
Classifier: Development Status :: 3 - Alpha
Classifier: Framework :: Django :: 2.2
Classifier: Framework :: Django :: 3.2
Classifier: Intended Audience :: Developers
Classifier: License :: OSI Approved :: BSD License
Classifier: Natural Language :: English
Classifier: Programming Language :: Python :: 3.6
Classifier: Programming Language :: Python :: 3.7
Classifier: Programming Language :: Python :: 3.8
Classifier: Programming Language :: Python :: 3.9
License-File: LICENSE.md
Requires-Dist: Django (>=2.2)
Requires-Dist: django-model-utils (>=2.0)
